{
    "id": "longest_substring_without_repeating_characters",
    "title": "Longest Substring Without Repeating Characters",
    "description": "Given a string s, find the length of the longest substring without repeating characters.",
    "input_format": "A single string s.",
    "output_format": "An integer representing the length.",
    "constraints": {
        "s.length": "0 <= s.length <= 5 * 10^4"
    },
    "difficulty": "medium",
    "judge_mode": "str_compare_strip",
    "time_limit": 1,
    "sample_test_cases": [
        {
            "input": "abcabcbb",
            "output": "3"
        },
        {
            "input": "bbbbb",
            "output": "1"
        },
        {
            "input": "pwwkew",
            "output": "3"
        }
    ],
    "hidden_test_cases": [
        {
            "input": "@wyt8cl7!fte0@zwu6gzhz!scf2!uqvs",
            "output": "15"
        },
        {
            "input": "trmkriweq2dh3g31rh1lwisx47h5wu#yh0achbh#7mog54qwcmagzw87nenjrh6jk2@51#@mg0trpxt5pstdyokg6avjald0s",
            "output": "13"
        },
        {
            "input": "32bhd@q3yiyd0@ltqd00cbsl7vkdyq1kqi58xk9vxobox2d8w#s3la!!@kesez1dx8elxxg5dc5alomefn9bt",
            "output": "13"
        },
        {
            "input": "#g8sswy5t@@!52ajc2z28m83ptbipt9r297aanhpk4ww!ikoez@5g!bkdt0smo2d8u!#wyrgvpj8jya1e",
            "output": "18"
        },
        {
            "input": "mdymg#h0tv7kxlvl@",
            "output": "13"
        },
        {
            "input": "wnq7n@6wna",
            "output": "6"
        },
        {
            "input": "jdeeeonpm3!cnjfzevhkt7mjzmxdyov55e8x71#@1cghg0we@6z1w8no30xgdovx67v9cfh9y9egv0kcs",
            "output": "15"
        },
        {
            "input": "z4pvhd4x6f#zplbxm0phe8jc8d@u!rxcs@u5nnx!p7@na@7k2ev3@#6mbtsvld#8l7wgw2dwh@swd1d4tul@b#zlsq24l@",
            "output": "13"
        },
        {
            "input": "4!l5vl1k04k8ifzp1mdnx#8924fczpc!u5#gbl46qpd65n79jzocg",
            "output": "14"
        },
        {
            "input": "qam12jdqf83mhnyw0#7vfpm#a7vbu5d5ipeoxb#3aomr0w@qaz6gc80emh@5xj63",
            "output": "17"
        },
        {
            "input": "atvwv0m3i5io@hx0z!psuzdw7z0s!80wk2et",
            "output": "12"
        },
        {
            "input": "wydayaeyxyvv99ii#kgiirjhfow9v2wai93#t594vbjwviojqcn7#s8l25xwamv87vff1fuzscbr27rjchhi8ing3ozc",
            "output": "18"
        },
        {
            "input": "5bivc3ny8nwbdxp#99gr@ha",
            "output": "10"
        },
        {
            "input": "zcxejvafi320sia!u23a5#rmrhrck3lq!",
            "output": "13"
        },
        {
            "input": "8ood2f1rgqef9fxgkyc@ufd9x0y@kot4bltwed07p7mojfdm0#f6fmin@2ul4ap78x!7!23ftczgvw03uw9#95#5b8j!u@",
            "output": "16"
        },
        {
            "input": "8ybk9qff6gsi2ltcb0g@559kr@004t4x22hd339dx9tscp#xnnmpryi@i#ll8#z16rnhejuq8hx4xvm#ajtodb5eqtv",
            "output": "14"
        },
        {
            "input": "xo5wz9a@63vwq5z31#1xc@2td4i3qu9v94@8bk",
            "output": "15"
        },
        {
            "input": "wr3k5301una8b8u@adn79oloi#",
            "output": "11"
        },
        {
            "input": "7fb7!xqbngpz4#idatz@f@gsky6ly!2besabvxzsl2",
            "output": "15"
        },
        {
            "input": "ll49uv4rdr@4",
            "output": "6"
        },
        {
            "input": "5ejlj9jsw4t9dat3fm!1aq7632766djx4k6qhpls74m@2qrg8kf!7b3nljhk32q@fgx@a4!b0g@let#i3##3wni@43#hph",
            "output": "18"
        },
        {
            "input": "@3m6vi6byyxjkkw0dnezv49vrs58nc#wl05k0att3xw7t!tsqkmfun3fhk8",
            "output": "13"
        },
        {
            "input": "bd6@jqyierdqmxu!0lurfhjxio5!3c#j2si24u7ciir06qwky",
            "output": "15"
        },
        {
            "input": "j91odtjr788edz191@!w4j@sr1o740i#h2!t!gg26778jy3vd",
            "output": "15"
        },
        {
            "input": "bn4yugmn@lv#ibc60r8u54nc!x4@h33sx2pid2an5iwind9bfba73m3ap5#zxu8h1x7kn3npym0bb24x",
            "output": "17"
        },
        {
            "input": "dncf6c8m!##nmqd9uo",
            "output": "8"
        },
        {
            "input": "ove2wse93elkam@bchu@s@3l70",
            "output": "12"
        },
        {
            "input": "j94a5!eg!0!8jjcvv",
            "output": "8"
        },
        {
            "input": "36@wu0un73ghcslqkblyi8m0p6wujg",
            "output": "15"
        },
        {
            "input": "jv!qdi2o52wmxdceiu@t9omtjv#20i23l!7hh7w6md4599d94s4iv6577r87i50ekp1",
            "output": "14"
        },
        {
            "input": "srukv1ixtc6s9tfgfvv!9pk@i!62o0#z#yqu25sdy2j5o2j",
            "output": "12"
        },
        {
            "input": "j4nx26xtjtlozlc#fxa@sxshe@twtduu!#p9@p8umcy@8@ez93vy@won8@obxa8neyxaxs!k03wtfae49",
            "output": "13"
        },
        {
            "input": "b3moe#cp516@tokfmz11aq59fvk",
            "output": "14"
        },
        {
            "input": "epnyx28fa5xivf!7mw8s8pd52f9fj@rcip!ngq",
            "output": "12"
        },
        {
            "input": "laifk7lyup1mr8ftw3b6l74q4p2gsbpx3@fsn0i!1k7kppl7d5puc#fewm48u5vsiys@89mfcph0r4t7j!va24s4",
            "output": "21"
        },
        {
            "input": "caglo3djbkwbq24c0qbkf2pkt7tg2q4zzuizxumi2mf4wi57h!4!p63j7xc4w4mp8d01fxdto#ef#rpj5ndyh37z@w6",
            "output": "17"
        },
        {
            "input": "hca@m81e7@hcvmv",
            "output": "9"
        },
        {
            "input": "heiy2ekff7dcgwd8xtraelyik33k6tdx9#2##t6pot#lrmd!576wjz@7bmqdjsmb0mur2otsxywymq5xvhue9to9rmo7hb",
            "output": "16"
        },
        {
            "input": "sxq7zi@pb429nhvzcv2mr2d",
            "output": "15"
        },
        {
            "input": "x!!grl1@47#7o7r#k0l80o",
            "output": "9"
        },
        {
            "input": "@#sz0x@22vgcmstadzc@zlow3b8sek1dn89772kmaq2ycn",
            "output": "15"
        },
        {
            "input": "u5bswlkk2eay#y3q5!o6kuj@#ow8uuh7c9408fzntwwg12tzu2nex",
            "output": "13"
        },
        {
            "input": "nr!3x@qh6oqdnjflo",
            "output": "10"
        },
        {
            "input": "13tkdrb2t1c5ekjf7!zzzqzs1auext!g4x5krlv8v29ox7!3q",
            "output": "15"
        },
        {
            "input": "ry0lp2!bco2xnhp0evd!ceh#s5evr0srow4hx0qlnmy@us96ul",
            "output": "17"
        },
        {
            "input": "9hq6diz21wt@0tk0uef@934z663ijb0!noafj0w2",
            "output": "13"
        },
        {
            "input": "ti8umrmsgx5g1rnxwzdmn1xkdv3d0phu97jlwr82peikdx8qe3jpvlqo6d38p0odp#oyxjh@8h7i@",
            "output": "16"
        },
        {
            "input": "j8v4tub3e6hvcy3ddkcsrwzy5bv@zqgp",
            "output": "12"
        },
        {
            "input": "@#3ucsuham@mu0@7440vur@12lk5sqjd1iqvqn31ny5t543nsoxbx7tks8uzvp",
            "output": "15"
        },
        {
            "input": "cat0u@yb1p8md780g1y2jjm3#xdybpg!ufx780zbkfv3abqre",
            "output": "14"
        },
        {
            "input": "u36c5vssscwc4@q4xojbesaynqhnybxs95@zo5!tf5@q4zkvdf93cs!r21l7keiauddej84r5xlzvwz90kjaw@ct5@ar3",
            "output": "19"
        },
        {
            "input": "o@pm8qtdj!uexj5muo!36f22l#hy@kj#qef8mmbo1emh!f!pl4sw!6bt",
            "output": "13"
        },
        {
            "input": "u3eu3ym4ft",
            "output": "8"
        },
        {
            "input": "48bf5b2irguv578w4b@d3thmhf544evcobp#200gmaicqt1gtz0ns",
            "output": "18"
        },
        {
            "input": "@5a2avzn8i5hg0j8unbowqd0t6pp!niwa2odxm1ysor@bzxak3mjldg80y@cc#125f08et7gyvar7235cpgbft1arqf",
            "output": "19"
        },
        {
            "input": "19f2nxnerm9yaijn6@3ovj6swmyvhj2i0aigxj3ckn6gmhq238bewf4qz3s5!nbfqz8z3fni",
            "output": "16"
        },
        {
            "input": "ajntr5cng98ly",
            "output": "10"
        },
        {
            "input": "sbyupv#m121bn9ksgf0kjr15badlot7hm08z!9izq7lnd1bjm",
            "output": "20"
        },
        {
            "input": "k1naa302qjr7#wk6v1vo",
            "output": "14"
        },
        {
            "input": "5qo94drsgy#9l1efcv2h!i",
            "output": "18"
        },
        {
            "input": "8sso2!h1aa",
            "output": "7"
        },
        {
            "input": "7r2#!474ihvhn44pcws2ihfs3m@x2j9xyq3",
            "output": "11"
        },
        {
            "input": "6ba0k!ptt6fq2lgajaetm!cpxexiu4bse65qv0p4vtzmj",
            "output": "13"
        },
        {
            "input": "ehb0hbb6hgjrz15qb!snsimizmf@pqae",
            "output": "13"
        },
        {
            "input": "uh!qa@o6#gwi5x8hwzhizx5uenhhuhbn!jt#fscyx0p1vwevzwk29gui6346#@u1",
            "output": "19"
        },
        {
            "input": "frlibb7qmwyk2qa9d9y@li4zk9kwt8ppuugf@qv@1k5d#2gx3qsxi3akk!8i!siec7z8r!4irc",
            "output": "13"
        },
        {
            "input": "lad7fa8b2l87@mh2dr1@2yguxaidbq7lsn36!f5vco2ddxqeblhshbx7fi@60z4e3p8x423gh#r4nsw9@cd0un9zas05p",
            "output": "25"
        },
        {
            "input": "@0d7m2sl2hb3",
            "output": "8"
        },
        {
            "input": "l@97olj1gqar2o6cru2oqft6!!eu0ezgtlzgqemf#85sq3chuxg3mdqr4wyjajq@ezatuwc2f",
            "output": "15"
        },
        {
            "input": "2xvbe7yysye@fumgspqt0wqfudm9bwj27a#a8!xeajf1py9n819dnz@yi@zpoevmfcc3n3xe3ge5yahlycgzw0",
            "output": "13"
        },
        {
            "input": "womw13u6r08mo#5n8ix",
            "output": "13"
        },
        {
            "input": "5btf9suhzfh03ccrmixo7!0diglcowfk6r@sa37m5jptoitletwu1ml0f1uh@7",
            "output": "23"
        },
        {
            "input": "fsajke8pvcov2durs0ptfsap8w8h@kpgy0u0hzasipg22!um9b4t9yae6ruz40bdkh1nwrxc7g#eiw9t37m",
            "output": "19"
        },
        {
            "input": "hw!7s77o59jyi4011rjm4mf214rujvnghf!w42w!#up1p0xwhwvmz5y18w1r2kyd6cpx1ix8tsxoutz!dyccnngevn",
            "output": "13"
        },
        {
            "input": "zwjumr9wde!dkiyp910p7b2m3qtwy#22zului5l3p2p2!zipubfleg1#j@xbxmlr",
            "output": "16"
        },
        {
            "input": "orut!f2bf6oj4lko",
            "output": "9"
        },
        {
            "input": "5jkpktw4dl8fno!g76vqjek8q5qzd",
            "output": "19"
        },
        {
            "input": "asbxr!d!vv14eqxy1yagg8f3c3go7#1sfsjapfrlyxia9zgl!ujq",
            "output": "12"
        },
        {
            "input": "27!2u3jys!x34w8ywd6sy22oz0znqklkfa5cl6l!oda!2kuwlu907gwy34uoxns2@68ilgj4i8jfe750g9ihikurozhs24",
            "output": "19"
        },
        {
            "input": "mvxsfo4mnyoof7lzkh8cqxec!br7a@@n97@fbe12xt2k5@5t64#d!cx@pme0vau5m198i7c5#!64sjg93m#v",
            "output": "17"
        },
        {
            "input": "s7ayzrzt2z0x2wo!6jw#u!61dkl#v0lg!vjwjras84sajchhxs@oz5jkvfe!mkd7sdnycsu5z54@7w6v0sfevadjw",
            "output": "14"
        },
        {
            "input": "mxegjrbe#5o!97o3jg6",
            "output": "11"
        },
        {
            "input": "frjoulfovccidbg!o3#x",
            "output": "10"
        },
        {
            "input": "qd766m9jxk85i!s@9e#@mb9lchxo@@vvf8q7yhk@i7kfybtlhm4mmqnlzyqfev@vo",
            "output": "12"
        },
        {
            "input": "giko8l8mzo95hzmqyctami5zql",
            "output": "11"
        },
        {
            "input": "typ@tq34cvbel3h@tlc04yf7sytii9jy",
            "output": "12"
        },
        {
            "input": "3jd0lnuac!0fe9y9kwt3p6q8lgc5gqasdgs!skw@ybv",
            "output": "14"
        },
        {
            "input": "bemcmrbcvbcsr2##qa43mcbibkij2exso08@c03c!jex7n!m1m7h8eurk9eft3@4q#io2vskl88b5",
            "output": "17"
        },
        {
            "input": "gur8fga1peweonnkvydap0znun86idnfwv",
            "output": "10"
        },
        {
            "input": "vwbvgs0@nop@fhc44g#dwtkzldf2i05pq8f75nt5s23i5lzexnw1s4eh9f0dp9j748#hzl",
            "output": "14"
        },
        {
            "input": "v40n6y6haro2ob9b#ry7m2n49e94ngq94dh2hbv7#91h8u0e2",
            "output": "12"
        },
        {
            "input": "p0fje#l0j346c3skwwz5g9kcj@r4y9x01tz#7y#ky1rl!#6bvu8",
            "output": "15"
        },
        {
            "input": "vzetghcpnx7oldqqi!veiyuifh3tbpf",
            "output": "15"
        },
        {
            "input": "#ae0wh2zb93q3@kkbu3rnaton8llckrtz@!aj16j68zscgjm2soh3es@nhz04vcgjfrk6pun85pkgd#i",
            "output": "19"
        },
        {
            "input": "@#cgj8mgdopwm3jb94fniyrw8rtxqg2i#hbr7l8wkcga45y!wy1jmaoicrch6f2n",
            "output": "18"
        },
        {
            "input": "kbc0wbkm244v#1fjkks9ymyjy",
            "output": "8"
        },
        {
            "input": "47p2r57xva!4a5z@9uc",
            "output": "10"
        },
        {
            "input": "unw9#h!@4snnvfcz#f#31207d0@m#uun0vg2ay0n2kr2g@sec6a",
            "output": "10"
        },
        {
            "input": "97aps6ku7z6@kmgf#bl0!jha3msmgraco0jjsx28g3t2xqe0bxmyapsjk2buwowyyve6pyunmz83wuxgii7bjzj@88oo",
            "output": "18"
        },
        {
            "input": "x4!idcwj3dc1@!hiimf8oww#esotyp##lnvu3xw0wv9h94t8nh0c7lrih0bc9bqenmdzbic6ghrn251cww",
            "output": "14"
        },
        {
            "input": "u!ytpeu26lzoa678e!5w!xia@e",
            "output": "12"
        },
        {
            "input": "c1r14ojv1y3yoopr!dawds4j2cpu254bac#qta87hfuj!cb@ddh",
            "output": "15"
        },
        {
            "input": "cwhjsi@jdkj6i#n932tfrlm1dx0vayb1rwfolujfgr!ksn1qswpn@tb7zq6l#ag0!jrl1k7gj@og44b9jtivxazrbt",
            "output": "22"
        },
        {
            "input": "xs!o7i536v@!ywl@57",
            "output": "12"
        },
        {
            "input": "ww21cgqhn8iygtb5rrd76gswbitmwjl@wgzopzy7pgdqd1yson677se8ljbvchoybs",
            "output": "12"
        },
        {
            "input": "x6m#wodvmajd0g!2yam!",
            "output": "10"
        },
        {
            "input": "9k34ara1g@6fohj2qhnf!ytfd#wn0w4",
            "output": "12"
        },
        {
            "input": "wyz7snckabuhwsnqzi01t0#5w3o0izqrxj!iwcphvdu04k#qfu#w5t4#6b7xvazra995pbct1qdlbm7fld",
            "output": "18"
        }
    ]
}