{
    "id": "reverse_string",
    "title": "Reverse a String",
    "description": "Reversing a string involves arranging its characters in the opposite order. For example, 'hello' becomes 'olleh'. In this problem, you are given a string `S`. Your task is to generate and output the reversed version of this string.",
    "input_format": "A single string S.",
    "output_format": "Output a single string representing the reversed version of the input string `S`.",
    "constraints": {
        "S": "1 <= length(S) <= 1000"
    },
    "judge_mode": "FIRST_FAIL",
    "time_limit": 1,
    "sample_test_cases": [
        {
            "input": "hello",
            "output": "olleh"
        },
        {
            "input": "world",
            "output": "dlrow"
        }
    ],
    "hidden_test_cases": [
        {
            "input": "adaegccfcd",
            "output": "dcfccgeada"
        },
        {
            "input": "gagdfcbadfgcbg",
            "output": "gbcgfdabcfdgag"
        },
        {
            "input": "acdadcfaabg",
            "output": "gbaafcdadca"
        },
        {
            "input": "feg",
            "output": "gef"
        },
        {
            "input": "ecegaf",
            "output": "fagece"
        },
        {
            "input": "dfegbfcdebdb",
            "output": "bdbedcfbgefd"
        },
        {
            "input": "gaefdfdc",
            "output": "cdfdfeag"
        },
        {
            "input": "eceddga",
            "output": "agddece"
        },
        {
            "input": "baeeacgdfbggc",
            "output": "cggbfdgcaeeab"
        },
        {
            "input": "afadebbfbdgcd",
            "output": "dcgdbfbbedafa"
        },
        {
            "input": "faabfedbca",
            "output": "acbdefbaaf"
        },
        {
            "input": "febgaecdgfcdd",
            "output": "ddcfgdceagbef"
        },
        {
            "input": "gfa",
            "output": "afg"
        },
        {
            "input": "gfbgbc",
            "output": "cbgbfg"
        },
        {
            "input": "ccfbbdegfc",
            "output": "cfgedbbfcc"
        },
        {
            "input": "ecafgcgg",
            "output": "ggcgface"
        },
        {
            "input": "ebegfega",
            "output": "agefgebe"
        },
        {
            "input": "edb",
            "output": "bde"
        },
        {
            "input": "bcbbbcbddbgbdf",
            "output": "fdbgbddbcbbbcb"
        },
        {
            "input": "effecefebcfc",
            "output": "cfcbefeceffe"
        },
        {
            "input": "agcceefgccgdadf",
            "output": "fdadgccgfeeccga"
        },
        {
            "input": "fdagefgeacb",
            "output": "bcaegfegadf"
        },
        {
            "input": "daaecadd",
            "output": "ddaceaad"
        },
        {
            "input": "bfcacbd",
            "output": "dbcacfb"
        },
        {
            "input": "ceecacceab",
            "output": "baeccaceec"
        },
        {
            "input": "fcfcdg",
            "output": "gdcfcf"
        },
        {
            "input": "cbbffadcfgcddd",
            "output": "dddcgfcdaffbbc"
        },
        {
            "input": "eaafg",
            "output": "gfaae"
        },
        {
            "input": "eabaefbecddcaf",
            "output": "facddcebfeabae"
        },
        {
            "input": "degaagfce",
            "output": "ecfgaaged"
        },
        {
            "input": "ccebfdffdegdg",
            "output": "gdgedffdfbecc"
        },
        {
            "input": "dagggacefbcgdcg",
            "output": "gcdgcbfecagggad"
        },
        {
            "input": "gdabfedebdbg",
            "output": "gbdbedefbadg"
        },
        {
            "input": "gdfg",
            "output": "gfdg"
        },
        {
            "input": "cdgfddgf",
            "output": "fgddfgdc"
        },
        {
            "input": "dfgacfagdgd",
            "output": "dgdgafcagfd"
        },
        {
            "input": "cfabfcbfecec",
            "output": "cecefbcfbafc"
        },
        {
            "input": "eggbgggdggacef",
            "output": "fecaggdgggbgge"
        },
        {
            "input": "geegdc",
            "output": "cdgeeg"
        },
        {
            "input": "baaae",
            "output": "eaaab"
        },
        {
            "input": "adefegcfggefbb",
            "output": "bbfeggfcgefeda"
        },
        {
            "input": "eaagggfcg",
            "output": "gcfgggaae"
        },
        {
            "input": "adcdgceaaf",
            "output": "faaecgdcda"
        },
        {
            "input": "gfeffg",
            "output": "gffefg"
        },
        {
            "input": "aefecfgf",
            "output": "fgfcefea"
        },
        {
            "input": "gadbag",
            "output": "gabdag"
        },
        {
            "input": "cebafebe",
            "output": "ebefabec"
        },
        {
            "input": "adbdccdcfdg",
            "output": "gdfcdccdbda"
        },
        {
            "input": "ffbdaegfdgbcce",
            "output": "eccbgdfgeadbff"
        },
        {
            "input": "dabfccegefccaaf",
            "output": "faaccfegeccfbad"
        },
        {
            "input": "ecdbgbdegccece",
            "output": "ececcgedbgbdce"
        },
        {
            "input": "beacb",
            "output": "bcaeb"
        },
        {
            "input": "bdcaebfebd",
            "output": "dbefbeacdb"
        },
        {
            "input": "dfecbcgebgccc",
            "output": "cccgbegcbcefd"
        },
        {
            "input": "gaegegdedgaedbd",
            "output": "dbdeagdedgegeag"
        },
        {
            "input": "agcfadcaegbb",
            "output": "bbgeacdafcga"
        },
        {
            "input": "deccb",
            "output": "bcced"
        },
        {
            "input": "fafcdeggcbbgced",
            "output": "decgbbcggedcfaf"
        },
        {
            "input": "bbeebce",
            "output": "ecbeebb"
        },
        {
            "input": "egcgbeafafef",
            "output": "fefafaebgcge"
        },
        {
            "input": "egbgba",
            "output": "abgbge"
        },
        {
            "input": "ebddd",
            "output": "dddbe"
        },
        {
            "input": "bgedeecff",
            "output": "ffceedegb"
        },
        {
            "input": "ggdbagaecebg",
            "output": "gbeceagabdgg"
        },
        {
            "input": "cfeecagecebd",
            "output": "dbecegaceefc"
        },
        {
            "input": "afcgcg",
            "output": "gcgcfa"
        },
        {
            "input": "gcfaacaba",
            "output": "abacaafcg"
        },
        {
            "input": "fdgdfagbdgggbf",
            "output": "fbgggdbgafdgdf"
        },
        {
            "input": "aafeebaa",
            "output": "aabeefaa"
        },
        {
            "input": "bgeeaad",
            "output": "daaeegb"
        },
        {
            "input": "ecc",
            "output": "cce"
        },
        {
            "input": "egcgaedfccga",
            "output": "agccfdeagcge"
        },
        {
            "input": "gcdgbccfgcdaf",
            "output": "fadcgfccbgdcg"
        },
        {
            "input": "baedaagadcff",
            "output": "ffcdagaadeab"
        },
        {
            "input": "gebd",
            "output": "dbeg"
        },
        {
            "input": "eagcbbfefca",
            "output": "acfefbbcgae"
        },
        {
            "input": "acadded",
            "output": "deddaca"
        },
        {
            "input": "becadafaf",
            "output": "fafadaceb"
        },
        {
            "input": "eedgcafgad",
            "output": "dagfacgdee"
        },
        {
            "input": "ggfbfcf",
            "output": "fcfbfgg"
        },
        {
            "input": "agg",
            "output": "gga"
        },
        {
            "input": "dcfbbeba",
            "output": "abebbfcd"
        },
        {
            "input": "agfbbdgeebf",
            "output": "fbeegdbbfga"
        },
        {
            "input": "agbfcfcbb",
            "output": "bbcfcfbga"
        },
        {
            "input": "gegdefcd",
            "output": "dcfedgeg"
        },
        {
            "input": "egbbc",
            "output": "cbbge"
        },
        {
            "input": "ababgbeggefe",
            "output": "efeggebgbaba"
        },
        {
            "input": "agggbcffdfba",
            "output": "abfdffcbggga"
        },
        {
            "input": "cdgd",
            "output": "dgdc"
        },
        {
            "input": "cdccdeggbebedd",
            "output": "ddebebggedccdc"
        },
        {
            "input": "edadaffca",
            "output": "acffadade"
        },
        {
            "input": "defadbe",
            "output": "ebdafed"
        },
        {
            "input": "gbaadgdg",
            "output": "gdgdaabg"
        },
        {
            "input": "aabbgebagabebb",
            "output": "bbebagabegbbaa"
        },
        {
            "input": "adbaadcadgdgb",
            "output": "bgdgdacdaabda"
        },
        {
            "input": "gdegddegcg",
            "output": "gcgeddgedg"
        },
        {
            "input": "caefcgc",
            "output": "cgcfeac"
        },
        {
            "input": "debca",
            "output": "acbed"
        },
        {
            "input": "dcgfefcecb",
            "output": "bcecfefgcd"
        },
        {
            "input": "eda",
            "output": "ade"
        },
        {
            "input": "bgdabdagffeafc",
            "output": "cfaeffgadbadgb"
        },
        {
            "input": "cgfdeeabedcfae",
            "output": "eafcdebaeedfgc"
        },
        {
            "input": "acbcfggedg",
            "output": "gdeggfcbca"
        },
        {
            "input": "egfgbgc",
            "output": "cgbgfge"
        },
        {
            "input": "cdcbeeacgeaccb",
            "output": "bccaegcaeebcdc"
        },
        {
            "input": "aaeec",
            "output": "ceeaa"
        },
        {
            "input": "dccadgg",
            "output": "ggdaccd"
        },
        {
            "input": "bcgafafdbbaaefe",
            "output": "efeaabbdfafagcb"
        },
        {
            "input": "ccgedbcaffcbb",
            "output": "bbcffacbdegcc"
        },
        {
            "input": "feggabga",
            "output": "agbaggef"
        },
        {
            "input": "cfeefggfgagcceg",
            "output": "geccgagfggfeefc"
        },
        {
            "input": "aecgbfaeagcgada",
            "output": "adagcgaeafbgcea"
        },
        {
            "input": "badggbdded",
            "output": "deddbggdab"
        },
        {
            "input": "gdbcabaggffbg",
            "output": "gbffggabacbdg"
        },
        {
            "input": "eecdcefg",
            "output": "gfecdcee"
        },
        {
            "input": "aaacgcgafc",
            "output": "cfagcgcaaa"
        },
        {
            "input": "cfggdcabce",
            "output": "ecbacdggfc"
        },
        {
            "input": "dcgededgg",
            "output": "ggdedegcd"
        },
        {
            "input": "egafbggcagabbc",
            "output": "cbbagacggbfage"
        },
        {
            "input": "dbccdafeegd",
            "output": "dgeefadccbd"
        },
        {
            "input": "fcdfgdbbfb",
            "output": "bfbbdgfdcf"
        },
        {
            "input": "fbcbcfdcg",
            "output": "gcdfcbcbf"
        },
        {
            "input": "cbb",
            "output": "bbc"
        },
        {
            "input": "beagdg",
            "output": "gdgaeb"
        },
        {
            "input": "fbb",
            "output": "bbf"
        },
        {
            "input": "fddbeae",
            "output": "eaebddf"
        },
        {
            "input": "egdc",
            "output": "cdge"
        },
        {
            "input": "dffcgdge",
            "output": "egdgcffd"
        },
        {
            "input": "eeccffcaa",
            "output": "aacffccee"
        },
        {
            "input": "adef",
            "output": "feda"
        },
        {
            "input": "gdff",
            "output": "ffdg"
        },
        {
            "input": "fegafc",
            "output": "cfagef"
        },
        {
            "input": "baagbddfbbdbbg",
            "output": "gbbdbbfddbgaab"
        },
        {
            "input": "eag",
            "output": "gae"
        },
        {
            "input": "gbebggbbebgacd",
            "output": "dcagbebbggbebg"
        },
        {
            "input": "gfgeab",
            "output": "baegfg"
        },
        {
            "input": "cedbbcccge",
            "output": "egcccbbdec"
        },
        {
            "input": "daeaefcddf",
            "output": "fddcfeaead"
        },
        {
            "input": "bfebgeccbg",
            "output": "gbccegbefb"
        },
        {
            "input": "bfgdcefddebcdb",
            "output": "bdcbeddfecdgfb"
        },
        {
            "input": "cegeabcb",
            "output": "bcbaegec"
        },
        {
            "input": "cbaecgagdbc",
            "output": "cbdgagceabc"
        },
        {
            "input": "ccdfdda",
            "output": "addfdcc"
        },
        {
            "input": "dfacfccgaf",
            "output": "fagccfcafd"
        },
        {
            "input": "cagfgdgdcagbcfc",
            "output": "cfcbgacdgdgfgac"
        },
        {
            "input": "abebccd",
            "output": "dccbeba"
        },
        {
            "input": "ddbb",
            "output": "bbdd"
        },
        {
            "input": "dafgddgggacf",
            "output": "fcagggddgfad"
        },
        {
            "input": "faaeeedag",
            "output": "gadeeeaaf"
        },
        {
            "input": "ffaedebecfaadbf",
            "output": "fbdaafcebedeaff"
        },
        {
            "input": "dggfefegaebeb",
            "output": "bebeagefefggd"
        },
        {
            "input": "gcefgcbfgcdgf",
            "output": "fgdcgfbcgfecg"
        },
        {
            "input": "dggbafebebfg",
            "output": "gfbebefabggd"
        },
        {
            "input": "cccaeaeef",
            "output": "feeaeaccc"
        },
        {
            "input": "bfeebcff",
            "output": "ffcbeefb"
        },
        {
            "input": "gfdggg",
            "output": "gggdfg"
        },
        {
            "input": "ddeegbb",
            "output": "bbgeedd"
        },
        {
            "input": "fabdfgda",
            "output": "adgfdbaf"
        },
        {
            "input": "abgfgcbfgg",
            "output": "ggfbcgfgba"
        },
        {
            "input": "eaebagfgfbb",
            "output": "bbfgfgabeae"
        }
    ],
    "difficulty": "easy"
}